fluidgpt/__init__.py
fluidgpt/fluidai_gpt_sdk/__init__.py
fluidgpt/fluidai_gpt_sdk/endpoints.cpython-38-darwin.so
fluidgpt/fluidai_gpt_sdk/jupyter_helper.cpython-38-darwin.so
fluidgpt/fluidai_gpt_sdk/prompt_list.cpython-38-darwin.so
fluidgpt/validation/__init__.py
fluidgpt/validation/authentication.cpython-38-darwin.so
fluidgpt/validation/credentials_authentication.cpython-38-darwin.so
fluidgpt-1.2.3.dist-info/METADATA
fluidgpt-1.2.3.dist-info/WHEEL
fluidgpt-1.2.3.dist-info/top_level.txt
fluidgpt-1.2.3.dist-info/RECORD
