Metadata-Version: 2.1
Name: fluidgpt
Version: 1.2.3
Summary: Run different validation tests on machine learning models.
Home-page: https://github.com/
Author: FluidAI
Author-email: info@fluid.ai
Classifier: Programming Language :: Python :: 3
Classifier: License :: OSI Approved :: GNU General Public License v3 or later (GPLv3+)
Classifier: Operating System :: OS Independent
Requires-Python: >=3.7
Requires-Dist: openai
Requires-Dist: pandas
Requires-Dist: numpy
Requires-Dist: Cython
Requires-Dist: ipywidgets
Requires-Dist: markdown
Requires-Dist: mdutils
Requires-Dist: jupyter
Requires-Dist: ipython
Requires-Dist: python-jose
